{"cameraMode":{"drawMode":0,"name":"Shaded","section":"Shading Mode"},"sceneLighting":false,"audioPlay":false,"sceneViewState":{"m_AlwaysRefresh":false,"showFog":true,"showSkybox":false,"showFlares":true,"showImageEffects":true,"showParticleSystems":true,"showVisualEffectGraphs":true,"m_FxEnabled":true},"in2DMode":false,"pivot":{"x":-11.447431564331055,"y":18.30286979675293,"z":5.402316093444824},"rotation":{"x":-0.013574653305113316,"y":0.5893070101737976,"z":-0.009912451729178429,"w":-0.8077569603919983},"size":20.055686950683595,"orthographic":false}