{"cameraMode":{"drawMode":0,"name":"Shaded","section":"Shading Mode"},"sceneLighting":true,"audioPlay":false,"sceneViewState":{"m_AlwaysRefresh":false,"showFog":true,"showSkybox":true,"showFlares":true,"showImageEffects":true,"showParticleSystems":true,"showVisualEffectGraphs":true,"m_FxEnabled":true},"in2DMode":false,"pivot":{"x":0.5891039967536926,"y":2.8654685020446779,"z":0.9387383460998535},"rotation":{"x":-0.10846792161464691,"y":0.7146894335746765,"z":-0.11372451484203339,"w":-0.6815844178199768},"size":1.1824780702590943,"orthographic":false}